[{
  "_id": {
    "$oid": "64bbc828599714eb2f5cc55a"
  },
  "title": "new update hghghhhhhhhhhhhhhhhhhhhhhhhhhhh task",
  "description": " updated updated updated updatedupdated updated updated",
  "status": "Doing",
  "userId": {
    "$oid": "64bbb3416dd9a3ea3d7c1849"
  },
  "assignTo": {
    "$oid": "64bbbfd53fcbaff3389abe0e"
  },
  "createdAt": {
    "$date": "2023-07-22T12:14:32.409Z"
  },
  "updatedAt": {
    "$date": "2023-07-22T13:23:06.520Z"
  },
  "__v": 0,
  "deadline": {
    "$date": "2023-07-24T16:30:00.000Z"
  }
},
{
  "_id": {
    "$oid": "64bbc84d599714eb2f5cc560"
  },
  "title": "fgfdgfd fdgfd g task",
  "description": "hgh h fgh gfh fghfgh j h gf hgfh fghfg",
  "status": "ToDo",
  "userId": {
    "$oid": "64bbb3416dd9a3ea3d7c1849"
  },
  "assignTo": {
    "$oid": "64bbbfd53fcbaff3389abe0e"
  },
  "createdAt": {
    "$date": "2023-07-22T12:15:09.865Z"
  },
  "updatedAt": {
    "$date": "2023-07-22T12:15:09.865Z"
  },
  "__v": 0
},
{
  "_id": {
    "$oid": "64bbc855599714eb2f5cc566"
  },
  "title": "fgfdgfd fdgfd g task",
  "status": "Doing",
  "userId": {
    "$oid": "64bbb3416dd9a3ea3d7c1849"
  },
  "assignTo": {
    "$oid": "64bbbfd53fcbaff3389abe0e"
  },
  "createdAt": {
    "$date": "2023-07-22T12:15:17.416Z"
  },
  "updatedAt": {
    "$date": "2023-07-22T12:15:17.416Z"
  },
  "__v": 0
},
{
  "_id": {
    "$oid": "64bbcf36b041329de976c934"
  },
  "title": "fgfdgfd fdgfd g task",
  "description": "hgh h fgh gfh fghfgh j h gf hgfh fghfg",
  "status": "Doing",
  "userId": {
    "$oid": "64bbb3416dd9a3ea3d7c1849"
  },
  "assignTo": {
    "$oid": "64bbbfd53fcbaff3389abe0e"
  },
  "deadline": {
    "$date": "2023-07-24T16:30:00.000Z"
  },
  "createdAt": {
    "$date": "2023-07-22T12:44:38.703Z"
  },
  "updatedAt": {
    "$date": "2023-07-22T12:44:38.703Z"
  },
  "__v": 0
}]